sweepLineRadin/__init__.py
SweepLine-1.5.dist-info/METADATA
SweepLine-1.5.dist-info/WHEEL
SweepLine-1.5.dist-info/top_level.txt
SweepLine-1.5.dist-info/RECORD
